setup.py
vdt/__init__.py
vdt.versionplugin.fpm.egg-info/PKG-INFO
vdt.versionplugin.fpm.egg-info/SOURCES.txt
vdt.versionplugin.fpm.egg-info/dependency_links.txt
vdt.versionplugin.fpm.egg-info/namespace_packages.txt
vdt.versionplugin.fpm.egg-info/requires.txt
vdt.versionplugin.fpm.egg-info/top_level.txt
vdt.versionplugin.fpm.egg-info/zip-safe
vdt/versionplugin/__init__.py
vdt/versionplugin/fpm/__init__.py
vdt/versionplugin/fpm/package.py