Metadata-Version: 1.0
Name: vdt.versionplugin.fpm
Version: 0.1.0
Summary: Version Increment Plugin that builds with fpm
Home-page: UNKNOWN
Author: Martijn Jacobs
Author-email: martijn@kamaramusic.nl
License: UNKNOWN
Platform: UNKNOWN
